{"nodes":[{"cover":0,"min_v":0.0,"max_v":0.2,"avg_v":0.174,"comp_len":177,"x":250.0,"y":250.0,"id":"mn0"},{"cover":1,"min_v":0.4,"max_v":0.4,"avg_v":0.4,"comp_len":17,"x":291.6667,"y":322.1688,"id":"mn1"},{"cover":1,"min_v":0.4,"max_v":0.4,"avg_v":0.4,"comp_len":1,"x":291.6667,"y":177.8312,"id":"mn2"},{"cover":1,"min_v":0.4,"max_v":0.4,"avg_v":0.4,"comp_len":12,"x":166.6667,"y":250.0,"id":"mn3"},{"cover":2,"min_v":0.6,"max_v":0.6,"avg_v":0.6,"comp_len":126,"x":250.0,"y":83.3333,"id":"mn4"},{"cover":2,"min_v":0.6,"max_v":0.6,"avg_v":0.6,"comp_len":43,"x":250.0,"y":416.6667,"id":"mn5"},{"cover":3,"min_v":0.8,"max_v":0.8,"avg_v":0.8,"comp_len":119,"x":164.495,"y":15.0768,"id":"mn6"},{"cover":3,"min_v":0.8,"max_v":1.0,"avg_v":0.9781,"comp_len":73,"x":335.505,"y":15.0768,"id":"mn7"},{"cover":3,"min_v":0.8,"max_v":1.0,"avg_v":0.8812,"comp_len":64,"x":314.7048,"y":491.4815,"id":"mn8"}],"links":[{"value":1,"source":"mn0","target":"mn2"},{"value":435,"source":"mn0","target":"mn3"},{"value":483,"source":"mn0","target":"mn1"},{"value":88,"source":"mn1","target":"mn5"},{"value":126,"source":"mn2","target":"mn4"},{"value":1581,"source":"mn4","target":"mn6"},{"value":23,"source":"mn4","target":"mn7"},{"value":734,"source":"mn5","target":"mn8"}],"info":{"component_method":"connected_components","link_method":"connectivity","cover_overlap":0.0,"cover_intervals":4,"cover":[{"level":0,"range":[0.0,0.25]},{"level":1,"range":[0.25,0.5]},{"level":2,"range":[0.5,0.75]},{"level":3,"range":[0.75,1.0]}],"compute_time":0.0482}}