{"directed":false,"multigraph":true,"graph":{},"nodes":[{"cover":{"level":0,"range":[0.0,0.25]},"min_value":0.0,"max_value":0.2486,"avg_value":0.1311,"component_count":136,"components":["532","853","511","857","519","485","521","837","498","517","886","872","493","880","869","841","870","530","822","883","490","815","897","859","882","856","873","528","495","874","879","487","902","864","508","860","522","905","823","504","814","820","904","900","888","486","502","526","906","497","513","889","878","843","819","884","908","868","907","514","529","876","818","865","515","881","518","835","850","499","896","501","877","849","854","489","834","866","509","894","505","855","903","840","821","842","527","506","909","851","898","852","512","845","839","892","496","516","838","816","817","510","531","824","525","494","500","887","524","895","503","523","491","520","858","899","863","890","507","484","846","885","891","488","901","861","862","836","492","875","847","871","893","844","867","848"],"x":250.0,"y":375.0,"id":"mapper_node_0"},{"cover":{"level":1,"range":[0.25,0.5]},"min_value":0.2511,"max_value":0.4991,"avg_value":0.376,"component_count":83,"components":["741","790","791","757","748","803","759","732","740","813","779","745","774","796","756","765","766","784","739","764","776","801","778","772","792","785","731","768","733","746","767","783","781","738","755","789","736","744","749","752","751","760","786","782","798","806","771","793","811","743","797","812","804","742","810","769","770","787","735","763","780","777","802","734","795","737","758","761","753","805","762","788","750","800","807","809","773","775","799","754","808","747","794"],"x":250.0,"y":250.0,"id":"mapper_node_1"},{"cover":{"level":2,"range":[0.5,0.75]},"min_value":0.5003,"max_value":0.5661,"avg_value":0.5202,"component_count":7,"components":["727","724","726","725","730","729","728"],"x":250.0,"y":125.0,"id":"mapper_node_2"},{"cover":{"level":3,"range":[0.75,1.0]},"min_value":0.8269,"max_value":1.0,"avg_value":0.9582,"component_count":82,"components":["709","701","685","678","694","664","681","698","686","696","691","720","692","708","690","706","675","657","703","648","677","660","643","707","661","672","717","655","674","688","653","668","647","666","718","646","644","670","662","682","673","665","719","721","683","710","699","697","716","711","713","669","651","723","687","722","714","684","671","650","658","702","705","656","659","693","652","679","680","676","663","645","700","654","667","649","642","715","704","695","689","712"],"x":426.7767,"y":73.2233,"id":"mapper_node_3"}],"links":[{"value":835,"source":"mapper_node_0","target":"mapper_node_1","key":0},{"value":1,"source":"mapper_node_0","target":"mapper_node_2","key":0},{"value":52,"source":"mapper_node_1","target":"mapper_node_3","key":0},{"value":252,"source":"mapper_node_1","target":"mapper_node_2","key":0},{"value":98,"source":"mapper_node_2","target":"mapper_node_3","key":0}],"info":{"component_method":"connected_components","link_method":"connectivity","cover_overlap":0.0,"cover_intervals":4,"compute_time":0.026}}