{"nodes":[{"cover":0,"min_v":0.0,"max_v":0.0,"avg_v":0.0,"comp_len":12,"x":250.0,"y":250.0,"id":"mn0"},{"cover":0,"min_v":0.0,"max_v":0.0,"avg_v":0.0,"comp_len":12,"x":330.4938,"y":228.4317,"id":"mn1"},{"cover":0,"min_v":0.0,"max_v":0.0,"avg_v":0.0,"comp_len":6,"x":413.4642,"y":217.4849,"id":"mn2"},{"cover":4,"min_v":0.25,"max_v":0.25,"avg_v":0.25,"comp_len":3,"x":370.7407,"y":217.6476,"id":"mn3"},{"cover":4,"min_v":0.25,"max_v":0.25,"avg_v":0.25,"comp_len":12,"x":363.2885,"y":197.1727,"id":"mn4"},{"cover":4,"min_v":0.25,"max_v":0.25,"avg_v":0.25,"comp_len":8,"x":279.4628,"y":220.5372,"id":"mn5"},{"cover":4,"min_v":0.25,"max_v":0.25,"avg_v":0.25,"comp_len":12,"x":279.4628,"y":279.4628,"id":"mn6"},{"cover":4,"min_v":0.25,"max_v":0.25,"avg_v":0.25,"comp_len":2,"x":220.5372,"y":279.4628,"id":"mn7"},{"cover":5,"min_v":0.25,"max_v":0.25,"avg_v":0.25,"comp_len":3,"x":410.0083,"y":203.3618,"id":"mn8"},{"cover":5,"min_v":0.25,"max_v":0.25,"avg_v":0.25,"comp_len":12,"x":395.77,"y":169.1984,"id":"mn9"},{"cover":5,"min_v":0.25,"max_v":0.25,"avg_v":0.25,"comp_len":8,"x":271.5683,"y":169.5062,"id":"mn10"},{"cover":5,"min_v":0.25,"max_v":0.25,"avg_v":0.25,"comp_len":12,"x":332.6204,"y":260.8772,"id":"mn11"},{"cover":5,"min_v":0.25,"max_v":0.25,"avg_v":0.25,"comp_len":2,"x":220.5372,"y":220.5372,"id":"mn12"},{"cover":9,"min_v":0.5,"max_v":0.5,"avg_v":0.5,"comp_len":6,"x":407.8217,"y":196.4268,"id":"mn13"},{"cover":9,"min_v":0.5,"max_v":0.5,"avg_v":0.5,"comp_len":2,"x":316.1128,"y":300.7301,"id":"mn14"},{"cover":9,"min_v":0.5,"max_v":0.5,"avg_v":0.5,"comp_len":1,"x":303.5732,"y":407.8217,"id":"mn15"},{"cover":9,"min_v":0.5,"max_v":0.5,"avg_v":0.5,"comp_len":2,"x":401.0513,"y":179.5636,"id":"mn16"},{"cover":9,"min_v":0.5,"max_v":0.5,"avg_v":0.5,"comp_len":4,"x":405.5967,"y":190.272,"id":"mn17"},{"cover":9,"min_v":0.5,"max_v":0.5,"avg_v":0.5,"comp_len":1,"x":483.1007,"y":159.6447,"id":"mn18"},{"cover":9,"min_v":0.5,"max_v":0.5,"avg_v":0.5,"comp_len":2,"x":281.8903,"y":326.99,"id":"mn19"},{"cover":10,"min_v":0.5,"max_v":0.5,"avg_v":0.5,"comp_len":6,"x":446.5349,"y":180.8855,"id":"mn20"},{"cover":10,"min_v":0.5,"max_v":0.5,"avg_v":0.5,"comp_len":2,"x":300.7301,"y":316.1128,"id":"mn21"},{"cover":10,"min_v":0.5,"max_v":0.5,"avg_v":0.5,"comp_len":1,"x":299.4236,"y":409.17,"id":"mn22"},{"cover":10,"min_v":0.5,"max_v":0.5,"avg_v":0.5,"comp_len":2,"x":403.4175,"y":184.8781,"id":"mn23"},{"cover":10,"min_v":0.5,"max_v":0.5,"avg_v":0.5,"comp_len":4,"x":443.502,"y":172.8005,"id":"mn24"},{"cover":10,"min_v":0.5,"max_v":0.5,"avg_v":0.5,"comp_len":1,"x":483.2972,"y":160.1535,"id":"mn25"},{"cover":10,"min_v":0.5,"max_v":0.5,"avg_v":0.5,"comp_len":2,"x":260.8772,"y":332.6204,"id":"mn26"},{"cover":14,"min_v":0.75,"max_v":0.75,"avg_v":0.75,"comp_len":1,"x":316.9666,"y":447.2771,"id":"mn27"},{"cover":14,"min_v":0.75,"max_v":0.75,"avg_v":0.75,"comp_len":4,"x":439.5753,"y":163.6056,"id":"mn28"},{"cover":14,"min_v":0.75,"max_v":0.75,"avg_v":0.75,"comp_len":3,"x":444.1683,"y":174.4921,"id":"mn29"},{"cover":14,"min_v":0.75,"max_v":0.75,"avg_v":0.75,"comp_len":4,"x":290.1799,"y":368.3663,"id":"mn30"},{"cover":14,"min_v":0.75,"max_v":0.75,"avg_v":0.75,"comp_len":4,"x":343.98,"y":332.4182,"id":"mn31"},{"cover":15,"min_v":0.75,"max_v":0.75,"avg_v":0.75,"comp_len":1,"x":315.2425,"y":447.854,"id":"mn32"},{"cover":15,"min_v":0.75,"max_v":0.75,"avg_v":0.75,"comp_len":4,"x":476.8833,"y":145.005,"id":"mn33"},{"cover":15,"min_v":0.75,"max_v":0.75,"avg_v":0.75,"comp_len":3,"x":444.8198,"y":176.1894,"id":"mn34"},{"cover":15,"min_v":0.75,"max_v":0.75,"avg_v":0.75,"comp_len":4,"x":311.7596,"y":404.8016,"id":"mn35"},{"cover":15,"min_v":0.75,"max_v":0.75,"avg_v":0.75,"comp_len":4,"x":380.5478,"y":353.6101,"id":"mn36"},{"cover":19,"min_v":1.0,"max_v":1.0,"avg_v":1.0,"comp_len":1,"x":369.7636,"y":365.9071,"id":"mn37"},{"cover":19,"min_v":1.0,"max_v":1.0,"avg_v":1.0,"comp_len":2,"x":482.903,"y":159.1364,"id":"mn38"},{"cover":19,"min_v":1.0,"max_v":1.0,"avg_v":1.0,"comp_len":2,"x":478.0896,"y":147.6519,"id":"mn39"},{"cover":19,"min_v":1.0,"max_v":1.0,"avg_v":1.0,"comp_len":2,"x":295.2401,"y":410.4092,"id":"mn40"},{"cover":19,"min_v":1.0,"max_v":1.0,"avg_v":1.0,"comp_len":2,"x":373.4919,"y":361.9265,"id":"mn41"}],"links":[{"value":6,"source":"mn0","target":"mn6"},{"value":6,"source":"mn0","target":"mn11"},{"value":4,"source":"mn0","target":"mn7"},{"value":4,"source":"mn0","target":"mn12"},{"value":4,"source":"mn0","target":"mn5"},{"value":4,"source":"mn0","target":"mn10"},{"value":12,"source":"mn1","target":"mn4"},{"value":12,"source":"mn1","target":"mn9"},{"value":4,"source":"mn1","target":"mn3"},{"value":4,"source":"mn1","target":"mn8"},{"value":4,"source":"mn1","target":"mn5"},{"value":4,"source":"mn1","target":"mn10"},{"value":1,"source":"mn2","target":"mn3"},{"value":1,"source":"mn2","target":"mn8"},{"value":1,"source":"mn2","target":"mn5"},{"value":1,"source":"mn2","target":"mn10"},{"value":6,"source":"mn3","target":"mn13"},{"value":6,"source":"mn3","target":"mn20"},{"value":2,"source":"mn3","target":"mn16"},{"value":2,"source":"mn3","target":"mn23"},{"value":6,"source":"mn3","target":"mn8"},{"value":4,"source":"mn4","target":"mn16"},{"value":4,"source":"mn4","target":"mn23"},{"value":50,"source":"mn4","target":"mn9"},{"value":4,"source":"mn4","target":"mn17"},{"value":4,"source":"mn4","target":"mn24"},{"value":3,"source":"mn5","target":"mn17"},{"value":3,"source":"mn5","target":"mn24"},{"value":22,"source":"mn5","target":"mn10"},{"value":1,"source":"mn5","target":"mn15"},{"value":1,"source":"mn5","target":"mn22"},{"value":1,"source":"mn5","target":"mn19"},{"value":1,"source":"mn5","target":"mn26"},{"value":4,"source":"mn6","target":"mn14"},{"value":4,"source":"mn6","target":"mn21"},{"value":50,"source":"mn6","target":"mn11"},{"value":4,"source":"mn6","target":"mn19"},{"value":4,"source":"mn6","target":"mn26"},{"value":2,"source":"mn7","target":"mn13"},{"value":2,"source":"mn7","target":"mn20"},{"value":1,"source":"mn7","target":"mn14"},{"value":1,"source":"mn7","target":"mn21"},{"value":2,"source":"mn7","target":"mn12"},{"value":6,"source":"mn8","target":"mn13"},{"value":6,"source":"mn8","target":"mn20"},{"value":2,"source":"mn8","target":"mn16"},{"value":2,"source":"mn8","target":"mn23"},{"value":4,"source":"mn9","target":"mn16"},{"value":4,"source":"mn9","target":"mn23"},{"value":4,"source":"mn9","target":"mn17"},{"value":4,"source":"mn9","target":"mn24"},{"value":3,"source":"mn10","target":"mn17"},{"value":3,"source":"mn10","target":"mn24"},{"value":1,"source":"mn10","target":"mn15"},{"value":1,"source":"mn10","target":"mn22"},{"value":1,"source":"mn10","target":"mn19"},{"value":1,"source":"mn10","target":"mn26"},{"value":4,"source":"mn11","target":"mn14"},{"value":4,"source":"mn11","target":"mn21"},{"value":4,"source":"mn11","target":"mn19"},{"value":4,"source":"mn11","target":"mn26"},{"value":2,"source":"mn12","target":"mn13"},{"value":2,"source":"mn12","target":"mn20"},{"value":1,"source":"mn12","target":"mn14"},{"value":1,"source":"mn12","target":"mn21"},{"value":2,"source":"mn13","target":"mn31"},{"value":2,"source":"mn13","target":"mn36"},{"value":10,"source":"mn13","target":"mn20"},{"value":2,"source":"mn13","target":"mn28"},{"value":2,"source":"mn13","target":"mn33"},{"value":4,"source":"mn14","target":"mn31"},{"value":4,"source":"mn14","target":"mn36"},{"value":2,"source":"mn14","target":"mn21"},{"value":2,"source":"mn15","target":"mn30"},{"value":2,"source":"mn15","target":"mn35"},{"value":1,"source":"mn15","target":"mn27"},{"value":1,"source":"mn15","target":"mn32"},{"value":4,"source":"mn16","target":"mn28"},{"value":4,"source":"mn16","target":"mn33"},{"value":2,"source":"mn16","target":"mn23"},{"value":8,"source":"mn17","target":"mn24"},{"value":5,"source":"mn17","target":"mn29"},{"value":5,"source":"mn17","target":"mn34"},{"value":1,"source":"mn18","target":"mn29"},{"value":1,"source":"mn18","target":"mn34"},{"value":1,"source":"mn18","target":"mn30"},{"value":1,"source":"mn18","target":"mn35"},{"value":4,"source":"mn19","target":"mn30"},{"value":4,"source":"mn19","target":"mn35"},{"value":2,"source":"mn19","target":"mn26"},{"value":2,"source":"mn20","target":"mn31"},{"value":2,"source":"mn20","target":"mn36"},{"value":2,"source":"mn20","target":"mn28"},{"value":2,"source":"mn20","target":"mn33"},{"value":4,"source":"mn21","target":"mn31"},{"value":4,"source":"mn21","target":"mn36"},{"value":2,"source":"mn22","target":"mn30"},{"value":2,"source":"mn22","target":"mn35"},{"value":1,"source":"mn22","target":"mn27"},{"value":1,"source":"mn22","target":"mn32"},{"value":4,"source":"mn23","target":"mn28"},{"value":4,"source":"mn23","target":"mn33"},{"value":5,"source":"mn24","target":"mn29"},{"value":5,"source":"mn24","target":"mn34"},{"value":1,"source":"mn25","target":"mn29"},{"value":1,"source":"mn25","target":"mn34"},{"value":1,"source":"mn25","target":"mn30"},{"value":1,"source":"mn25","target":"mn35"},{"value":4,"source":"mn26","target":"mn30"},{"value":4,"source":"mn26","target":"mn35"},{"value":8,"source":"mn28","target":"mn33"},{"value":2,"source":"mn28","target":"mn39"},{"value":4,"source":"mn29","target":"mn34"},{"value":2,"source":"mn29","target":"mn38"},{"value":6,"source":"mn30","target":"mn35"},{"value":2,"source":"mn30","target":"mn40"},{"value":2,"source":"mn31","target":"mn41"},{"value":1,"source":"mn31","target":"mn37"},{"value":8,"source":"mn31","target":"mn36"},{"value":2,"source":"mn33","target":"mn39"},{"value":2,"source":"mn34","target":"mn38"},{"value":2,"source":"mn35","target":"mn40"},{"value":2,"source":"mn36","target":"mn41"},{"value":1,"source":"mn36","target":"mn37"}],"info":{"component_method":"connected_components","link_method":"connectivity","cover_overlap":0.0,"cover_intervals":20,"cover":[{"level":0,"range":[0.0,0.05]},{"level":1,"range":[0.05,0.1]},{"level":2,"range":[0.1,0.15]},{"level":3,"range":[0.15,0.2]},{"level":4,"range":[0.2,0.25]},{"level":5,"range":[0.25,0.3]},{"level":6,"range":[0.3,0.35]},{"level":7,"range":[0.35,0.4]},{"level":8,"range":[0.4,0.45]},{"level":9,"range":[0.45,0.5]},{"level":10,"range":[0.5,0.55]},{"level":11,"range":[0.55,0.6]},{"level":12,"range":[0.6,0.65]},{"level":13,"range":[0.65,0.7]},{"level":14,"range":[0.7,0.75]},{"level":15,"range":[0.75,0.8]},{"level":16,"range":[0.8,0.85]},{"level":17,"range":[0.85,0.9]},{"level":18,"range":[0.9,0.95]},{"level":19,"range":[0.95,1.0]}],"compute_time":0.005}}